devnotes/__init__.py
devnotes/analyzer.py
devnotes/cli.py
devnotes/config.py
devnotes/diagrams.py
devnotes/tasks.py
devnotes/trello.py
devnotes/utils.py
devnotes-0.1.4.dist-info/METADATA
devnotes-0.1.4.dist-info/WHEEL
devnotes-0.1.4.dist-info/entry_points.txt
devnotes-0.1.4.dist-info/top_level.txt
devnotes-0.1.4.dist-info/RECORD
