Metadata-Version: 2.4
Name: devnotes
Version: 0.1.4
Summary: DevNotes is a command-line tool for developers to efficiently manage development notes, tasks, and project documentation. It enables organizing work, tracking progress of activities, and maintaining structured documentation directly from the development environment.
Author-email: Fabio Cantone <fabio@cantone.me>
License-Expression: MIT
Keywords: development,notes,tasks,project management
Classifier: Programming Language :: Python :: 3
Classifier: Operating System :: OS Independent
Requires-Python: >=3.8
Requires-Dist: typer>=0.9.0
Requires-Dist: rich>=13.0.0
Requires-Dist: pyyaml>=6.0
Requires-Dist: prompt-toolkit>=3.0.0
Requires-Dist: python-dateutil>=2.8.0
Requires-Dist: requests
Provides-Extra: dev
Requires-Dist: pytest>=7.0.0; extra == "dev"
Requires-Dist: pytest-cov>=4.0.0; extra == "dev"
Requires-Dist: black>=23.0.0; extra == "dev"
Requires-Dist: isort>=5.0.0; extra == "dev"
Requires-Dist: flake8>=6.0.0; extra == "dev"
